odoo8_addon_l10n_it_fatturapa_out_ddt-8.0.2.0.0-nspkg.pth
odoo_addons/l10n_it_fatturapa_out_ddt/README.rst
odoo_addons/l10n_it_fatturapa_out_ddt/__init__.py
odoo_addons/l10n_it_fatturapa_out_ddt/__openerp__.py
odoo_addons/l10n_it_fatturapa_out_ddt/i18n/it.po
odoo_addons/l10n_it_fatturapa_out_ddt/i18n/l10n_it_fatturapa_out_ddt.pot
odoo_addons/l10n_it_fatturapa_out_ddt/readme/CONTRIBUTORS.rst
odoo_addons/l10n_it_fatturapa_out_ddt/readme/DESCRIPTION.rst
odoo_addons/l10n_it_fatturapa_out_ddt/readme/USAGE.rst
odoo_addons/l10n_it_fatturapa_out_ddt/static/description/icon.png
odoo_addons/l10n_it_fatturapa_out_ddt/static/description/index.html
odoo_addons/l10n_it_fatturapa_out_ddt/tests/__init__.py
odoo_addons/l10n_it_fatturapa_out_ddt/tests/test_fatturapa_ddt.py
odoo_addons/l10n_it_fatturapa_out_ddt/tests/data/IT06363391001_00006.xml
odoo_addons/l10n_it_fatturapa_out_ddt/tests/data/IT06363391001_00007.xml
odoo_addons/l10n_it_fatturapa_out_ddt/wizard/__init__.py
odoo_addons/l10n_it_fatturapa_out_ddt/wizard/wizard_export_fatturapa.py
odoo_addons/l10n_it_fatturapa_out_ddt/wizard/wizard_export_fatturapa_view.xml
odoo8_addon_l10n_it_fatturapa_out_ddt-8.0.2.0.0.dist-info/METADATA
odoo8_addon_l10n_it_fatturapa_out_ddt-8.0.2.0.0.dist-info/WHEEL
odoo8_addon_l10n_it_fatturapa_out_ddt-8.0.2.0.0.dist-info/namespace_packages.txt
odoo8_addon_l10n_it_fatturapa_out_ddt-8.0.2.0.0.dist-info/top_level.txt
odoo8_addon_l10n_it_fatturapa_out_ddt-8.0.2.0.0.dist-info/RECORD
