Metadata-Version: 2.1
Name: odoo8-addon-l10n-it-fatturapa-out-ddt
Version: 8.0.2.0.0
Summary: Modulo ponte tra emissione fatture elettroniche e DDT
Home-page: https://github.com/OCA/l10n-italy/tree/10.0/l10n_it_fatturapa_out_ddt
Author: Agile Business Group, Odoo Community Association (OCA)
Author-email: support@odoo-community.org
License: LGPL-3
Platform: UNKNOWN
Classifier: Programming Language :: Python
Classifier: Framework :: Odoo
Classifier: License :: OSI Approved :: GNU Lesser General Public License v3 (LGPLv3)
Classifier: Development Status :: 4 - Beta
Requires-Python: ~=2.7
Requires-Dist: odoo8-addon-l10n-it-ddt
Requires-Dist: odoo8-addon-l10n-it-ddt-delivery
Requires-Dist: odoo8-addon-l10n-it-fatturapa-out
Requires-Dist: odoo8-addon-stock-picking-invoice-link
Requires-Dist: odoo (<9.0a,>=8.0a)
